muuk_maintenance/__init__.py
muuk_maintenance/server.py
muuk_maintenance/utils.py
muuk_maintenance-0.1.3.dist-info/METADATA
muuk_maintenance-0.1.3.dist-info/WHEEL
muuk_maintenance-0.1.3.dist-info/entry_points.txt
muuk_maintenance-0.1.3.dist-info/top_level.txt
muuk_maintenance-0.1.3.dist-info/RECORD
