Metadata-Version: 2.4
Name: muuk-maintenance
Version: 0.1.3
Summary: MCP server for analyzing and repairing E2E test failures
Author-email: MuukTest <support@muuktest.com>
Project-URL: Homepage, https://muuktest.com
Keywords: mcp,testing,playwright,e2e,test-repair,ai,automation,muuktest,maintenance
Classifier: Development Status :: 4 - Beta
Classifier: Intended Audience :: Developers
Classifier: License :: OSI Approved :: MIT License
Classifier: Programming Language :: Python :: 3
Classifier: Programming Language :: Python :: 3.10
Classifier: Programming Language :: Python :: 3.11
Classifier: Programming Language :: Python :: 3.12
Classifier: Programming Language :: Python :: 3.13
Classifier: Topic :: Software Development :: Testing
Requires-Python: >=3.10
Requires-Dist: mcp>=1.0.0
Requires-Dist: requests>=2.28.0
Requires-Dist: requests-aws4auth>=1.2.0
